README.rst
setup.py
PBPWScraper.egg-info/PKG-INFO
PBPWScraper.egg-info/SOURCES.txt
PBPWScraper.egg-info/dependency_links.txt
PBPWScraper.egg-info/requires.txt
PBPWScraper.egg-info/top_level.txt
presets/__init__.py
presets/pastebin.py
scraper/__init__.py
scraper/filter.py
scraper/scraper.py