Metadata-Version: 1.0
Name: PBPWScraper
Version: 1.0.2
Summary: A simple scraper of the public posts on pastebin. It looks for passwords.
Home-page: https://bitbucket.org/cshortt/pastebin-scraper/
Author: Caleb Shortt
Author-email: caleb@rgauge.com
License: UNKNOWN
Keywords: pastebin,scraperpython,password
Platform: UNKNOWN
